ArtSciColor/__init__.py
ArtSciColor/_version.py
ArtSciColor/auxiliary.py
ArtSciColor/color.py
ArtSciColor/constants.py
ArtSciColor/fingerprint.py
ArtSciColor/fingerprintWrappers.py
ArtSciColor/image.py
ArtSciColor/paths.py
ArtSciColor/superscale.py
ArtSciColor/swatches.py
ArtSciColor/data/DB.bz
ArtSciColor/data/DB.csv
ArtSciColor/data/SWATCHES.bz
ArtSciColor-0.3.4.0.dist-info/LICENSE
ArtSciColor-0.3.4.0.dist-info/METADATA
ArtSciColor-0.3.4.0.dist-info/WHEEL
ArtSciColor-0.3.4.0.dist-info/top_level.txt
ArtSciColor-0.3.4.0.dist-info/RECORD
