Metadata-Version: 2.1
Name: ArtSciColor
Version: 0.3.4.0
Summary: Color palettes for scientific purposes
Home-page: https://github.com/Chipdelmal/ArtSciColor
Author: chipdelmal
Author-email: chipdelmal@gmail.com
Classifier: Programming Language :: Python :: 3
Classifier: License :: OSI Approved :: Apache Software License
Classifier: Operating System :: OS Independent
Requires-Python: >=3.10
License-File: LICENSE
Requires-Dist: matplotlib >=3.3.2
Requires-Dist: colour >=0.1.5
Requires-Dist: colorir
Requires-Dist: Pillow
Requires-Dist: opencv-python
Requires-Dist: super-image
Requires-Dist: scikit-learn
Requires-Dist: numpy
Requires-Dist: pandas
Requires-Dist: compress-pickle
